tsfm-0.9.7.dist-info/DESCRIPTION.rst
tsfm-0.9.7.dist-info/METADATA
tsfm-0.9.7.dist-info/entry_points.txt
tsfm-0.9.7.dist-info/RECORD
tsfm-0.9.7.dist-info/WHEEL
tsfm-0.9.7.dist-info/metadata.json
tsfm-0.9.7.dist-info/top_level.txt
tsfm/nsb_entropy.py
tsfm/exact.cpython-36m-x86_64-linux-gnu.so
tsfm/_version.py
tsfm/__init__.py
tsfm/MolecularInformation.py
tsfm/tsfm.py
tsfm/eps/Template.eps
tsfm/eps/inverse_template.eps
