Metadata-Version: 2.0
Name: tsfm
Version: 0.9.7
Summary: tRNA structure function mapper
Home-page: https://github.com/tlawrence3/tsfm
Author: Travis J. Lawrence and David H. Ardell
Author-email: tlawrence3@ucmerced.edu
License: LGPLv3
Platform: UNKNOWN
Classifier: Development Status :: 4 - Beta
Classifier: Environment :: Console
Classifier: Intended Audience :: Science/Research
Classifier: License :: OSI Approved :: GNU Lesser General Public License v3 (LGPLv3)
Classifier: Natural Language :: English
Classifier: Operating System :: MacOS :: MacOS X
Classifier: Operating System :: POSIX :: Linux
Classifier: Programming Language :: Python :: 3.4
Classifier: Programming Language :: Python :: 3.5
Classifier: Programming Language :: Python :: 3.6
Classifier: Programming Language :: Python :: Implementation :: CPython
Classifier: Topic :: Scientific/Engineering :: Bio-Informatics
Requires-Python: ~=3.4
Requires-Dist: cython
Requires-Dist: numpy
Requires-Dist: scipy
Requires-Dist: pandas
Requires-Dist: patsy
Requires-Dist: mpmath
Requires-Dist: statsmodels
